liquibase/__init__.py
liquibase/liquibase.py
liquibase/bin/ABOUT.txt
liquibase/bin/GETTING_STARTED.txt
liquibase/bin/LICENSE.txt
liquibase/bin/README.txt
liquibase/bin/UNINSTALL.txt
liquibase/bin/changelog.txt
liquibase/bin/liquibase
liquibase/bin/liquibase.bat
liquibase/bin/lpm
liquibase/bin/examples/start-h2
liquibase/bin/examples/start-h2.bat
liquibase/bin/examples/json/blank-changelog.json
liquibase/bin/examples/json/example-changelog.json
liquibase/bin/examples/json/example-changeset-json.txt
liquibase/bin/examples/json/liquibase.advanced.flowfile.yaml
liquibase/bin/examples/json/liquibase.checks-package.yaml
liquibase/bin/examples/json/liquibase.customlogdata.yaml
liquibase/bin/examples/json/liquibase.endstage.flow
liquibase/bin/examples/json/liquibase.flowfile.yaml
liquibase/bin/examples/json/liquibase.flowvariables.yaml
liquibase/bin/examples/json/liquibase.properties
liquibase/bin/examples/sql/blank-changelog.sql
liquibase/bin/examples/sql/example-changelog.sql
liquibase/bin/examples/sql/example-changeset-sql.txt
liquibase/bin/examples/sql/liquibase.advanced.flowfile.yaml
liquibase/bin/examples/sql/liquibase.checks-package.yaml
liquibase/bin/examples/sql/liquibase.customlogdata.yaml
liquibase/bin/examples/sql/liquibase.endstage.flow
liquibase/bin/examples/sql/liquibase.flowfile.yaml
liquibase/bin/examples/sql/liquibase.flowvariables.yaml
liquibase/bin/examples/sql/liquibase.properties
liquibase/bin/examples/sql/liquibase.psql.conf
liquibase/bin/examples/sql/liquibase.sqlcmd.conf
liquibase/bin/examples/sql/liquibase.sqlplus.conf
liquibase/bin/examples/xml/blank-changelog.xml
liquibase/bin/examples/xml/example-changelog.xml
liquibase/bin/examples/xml/example-changeset-xml.txt
liquibase/bin/examples/xml/liquibase.advanced.flowfile.yaml
liquibase/bin/examples/xml/liquibase.checks-package.yaml
liquibase/bin/examples/xml/liquibase.customlogdata.yaml
liquibase/bin/examples/xml/liquibase.endstage.flow
liquibase/bin/examples/xml/liquibase.flowfile.yaml
pyliquibasecli-4.29.0rc1.dist-info/METADATA
pyliquibasecli-4.29.0rc1.dist-info/WHEEL
pyliquibasecli-4.29.0rc1.dist-info/top_level.txt
pyliquibasecli-4.29.0rc1.dist-info/RECORD
