Metadata-Version: 2.4
Name: pyliquibasecli
Version: 4.29.0rc1
Summary: Liquibase adapter
Author-email: Klim Naidenov <pymirror@mail.ru>
Project-URL: Homepage, https://git@git.sourcecraft.dev/pymirror/pyliquibase.git
Project-URL: Issues, https://sourcecraft.dev/pymirror/pyliquibase/issues
Classifier: Operating System :: OS Independent
Requires-Python: >=3.0
